spinney/__about__.py
spinney/__init__.py
spinney/constants.py
spinney/defects/__init__.py
spinney/defects/concentration.py
spinney/defects/diagrams.py
spinney/defects/fnv.py
spinney/defects/kumagai.py
spinney/defects/madelung.py
spinney/io/__init__.py
spinney/io/vasp.py
spinney/io/wien2k.py
spinney/structures/__init__.py
spinney/structures/defectivesystem.py
spinney/structures/pointdefect.py
spinney/structures/wigner_seitz.py
spinney/tests/__init__.py
spinney/tests/spinney_run_tests.py
spinney/tests/defects/__init__.py
spinney/tests/defects/test_concentration.py
spinney/tests/defects/test_madelung.py
spinney/tests/defects/test_ws.py
spinney/tests/defects/resources/POSCAR_AlAs
spinney/tests/defects/resources/POSCAR_AlAs_333
spinney/tests/defects/resources/POSCAR_AlAs_333_WS_cell
spinney/tests/defects/resources/POSCAR_AlAs_333_region_in
spinney/tests/defects/resources/POSCAR_CaF2
spinney/tests/defects/resources/POSCAR_CsCl
spinney/tests/defects/resources/POSCAR_NaCl
spinney/tests/defects/resources/POSCAR_TiO2_rutile
spinney/tests/defects/resources/POSCAR_ZnO_w
spinney/tests/defects/resources/POSCAR_ZnO_w_333
spinney/tests/defects/resources/POSCAR_ZnO_w_333_WS_cell
spinney/tests/defects/resources/POSCAR_ZnO_w_333_region_in
spinney/tests/defects/resources/dos_ticosb
spinney/tests/defects/resources/dos_tio2_down
spinney/tests/defects/resources/dos_tio2_up
spinney/tests/structures/__init__.py
spinney/tests/structures/test_pointdefect.py
spinney/tests/structures/resources/found_Delta_Ti.txt
spinney/tests/structures/resources/calculations_results/O2/OUTCAR
spinney/tests/structures/resources/calculations_results/O_Ti_-1/OUTCAR
spinney/tests/structures/resources/calculations_results/O_Ti_-2/OUTCAR
spinney/tests/structures/resources/calculations_results/O_Ti_-3/OUTCAR
spinney/tests/structures/resources/calculations_results/O_Ti_-4/OUTCAR
spinney/tests/structures/resources/calculations_results/O_Ti_0/OUTCAR
spinney/tests/structures/resources/calculations_results/Ti/OUTCAR
Spinney-0.9a2.dist-info/LICENSE
Spinney-0.9a2.dist-info/METADATA
Spinney-0.9a2.dist-info/WHEEL
Spinney-0.9a2.dist-info/entry_points.txt
Spinney-0.9a2.dist-info/top_level.txt
Spinney-0.9a2.dist-info/RECORD
