Metadata-Version: 2.1
Name: Spinney
Version: 0.9a2
Summary: Spinney: a Python package for assisting with first-principles simulations of point defects in solids.
Home-page: https://gitlab.com/Marrigoni/spinney
Author: Marco Arrigoni
Author-email: marco.arrigoni@outlook.de
License: UNKNOWN
Platform: UNKNOWN
Classifier: Development Status :: 3 - Alpha
Classifier: Operating System :: OS Independent
Classifier: Intended Audience :: Science/Research
Classifier: License :: OSI Approved :: MIT License
Classifier: Topic :: Scientific/Engineering :: Chemistry
Classifier: Topic :: Scientific/Engineering :: Physics
Classifier: Programming Language :: Python :: 3
Requires-Python: >=3.4
Requires-Dist: ase (>=3.18)
Requires-Dist: numpy (>=1.12)
Requires-Dist: matplotlib (>=3.1.0)
Requires-Dist: scipy (>=1.4)
Requires-Dist: pandas (>=0.25)
